repoze.vhm-0.16-py3.8-nspkg.pth
repoze/vhm/__init__.py
repoze/vhm/constants.py
repoze/vhm/middleware.py
repoze/vhm/utils.py
repoze/vhm/tests/__init__.py
repoze/vhm/tests/test_middleware.py
repoze/vhm/tests/test_utils.py
repoze.vhm-0.16.dist-info/LICENSE.txt
repoze.vhm-0.16.dist-info/METADATA
repoze.vhm-0.16.dist-info/WHEEL
repoze.vhm-0.16.dist-info/entry_points.txt
repoze.vhm-0.16.dist-info/namespace_packages.txt
repoze.vhm-0.16.dist-info/top_level.txt
repoze.vhm-0.16.dist-info/RECORD
